mingflow
